{
  "name": {
    "tr": "Almanya",
    "en": "Germany"
  },
  "status": "play",
  "category": "Avrupa Ülkeleri",
  "id": "almanya",
  "url": "",
  "path": "almanya",
  "index": 2,
  "icon": "home",
  "desing": {
    "header": [],
    "body": [],
    "footer": []
  },
  "pathnext": "",
  "img": "logo.png",
  "description": {
    "tr": "Almanya çıkışlı yüklerde UK konsolidasyon veya doğrudan hat alternatifleri.",
    "en": "Germany-origin cargo via UK consolidation or direct strings."
  },
  "desc": {},
  "keyword": {
    "tr": "almanya UK hub turkiye besleme",
    "en": "germany feeder uk hub turkey"
  },
  "text": {
    "tr": "<p><strong>Marka ve SEO ayrımı:</strong> Bu içerik <strong>İngiltere'den Türkiye'ye (UK→TR)</strong> güzergâhına özeldir. <strong>Türkiye çıkışlı</strong> Avrupa/İngiltere taşımacılığı için <strong>hanbroscargo.com</strong> sitesindeki Han Bros Cargo içerikleri kullanılır; iki alan adı farklı yön ve anahtar kelime setine sahiptir.</p><p>Bu site UK→TR sözleşmesini öne çıkarır; Almanya çıkışı için güzergâh birleştirme teklifte netleştirilir.</p>",
    "en": "<p><strong>Brand and SEO separation:</strong> This page targets the <strong>United Kingdom to Turkey (UK→TR)</strong> lane. For <strong>Turkey-origin</strong> shipping to Europe/UK, use Han Bros Cargo on <strong>hanbroscargo.com</strong>; each domain uses distinct keywords and corridor messaging.</p><p>This site foregrounds UK→TR contracting; Germany-origin routing is clarified per quote.</p>"
  },
  "update": "2026-05-08T05:40:46.629Z",
  "date": "2026-05-08T05:18:35.730Z",
  "title": {
    "tr": "Almanya",
    "en": "Germany"
  }
}
